odoo/addons/website_sale_product_name_fixed_height/README.rst
odoo/addons/website_sale_product_name_fixed_height/__init__.py
odoo/addons/website_sale_product_name_fixed_height/__manifest__.py
odoo/addons/website_sale_product_name_fixed_height/i18n/it.po
odoo/addons/website_sale_product_name_fixed_height/i18n/website_sale_product_name_fixed_height.pot
odoo/addons/website_sale_product_name_fixed_height/models/__init__.py
odoo/addons/website_sale_product_name_fixed_height/models/res_config_settings.py
odoo/addons/website_sale_product_name_fixed_height/models/website.py
odoo/addons/website_sale_product_name_fixed_height/readme/CONFIGURE.rst
odoo/addons/website_sale_product_name_fixed_height/readme/CONTEXT.rst
odoo/addons/website_sale_product_name_fixed_height/readme/CONTRIBUTORS.rst
odoo/addons/website_sale_product_name_fixed_height/readme/DESCRIPTION.rst
odoo/addons/website_sale_product_name_fixed_height/static/description/icon.png
odoo/addons/website_sale_product_name_fixed_height/static/description/index.html
odoo/addons/website_sale_product_name_fixed_height/tests/__init__.py
odoo/addons/website_sale_product_name_fixed_height/tests/test_website_sale_fixed_name_height.py
odoo/addons/website_sale_product_name_fixed_height/views/res_config_settings_view.xml
odoo/addons/website_sale_product_name_fixed_height/views/website_sale_template.xml
odoo14_addon_website_sale_product_name_fixed_height-14.0.1.0.1.dev3.dist-info/METADATA
odoo14_addon_website_sale_product_name_fixed_height-14.0.1.0.1.dev3.dist-info/WHEEL
odoo14_addon_website_sale_product_name_fixed_height-14.0.1.0.1.dev3.dist-info/top_level.txt
odoo14_addon_website_sale_product_name_fixed_height-14.0.1.0.1.dev3.dist-info/RECORD
